{


  "lixeira": {
    "id": "lixeira",
    "nome": "Lixeira",
    "descricao": "Permite destruir itens por sucatas. Melhore-a para ter chance de encontrar itens no lixo e mais sucatas.",
    "max_level": 100,

    "custo": {
      "tempo": 5,
      "ouro": 50,
      "sucata": 10
    },
   
    "efeitos": {
      "tipo": "loot",
      "loot_table": [
        { "item": "queijo1", "qt": 1, "chance": 20, "lvl": 2 },
        { "item": "teia1", "qt": 1, "chance": 30, "lvl": 2 }
      ]
    }
  },

  "palha_amontoada": {
    "id": "palha_amontoada",
    "nome": "Palha Amontoada",
    "descricao": "Não é confortável, mas é possível descansar recuperando um pouco de vigor.",
    "max_level": 100,

    "custo": {
      "tempo": 7,
      "ouro": 100,
      "sucata": 20
    }
  },
   
    "mesa_de_caixote": {
    "id": "mesa_de_caixote",
    "nome": "Mesa de Caixote",
    "descricao": "Uma bancada improvisada feita com caixotes velhos. Permite realizar trabalhos manuais simples.",
    "max_level": 100, 
    "custo": {
      "tempo": 10,
      "ouro": 200,
      "sucata": 35
    },
    "efeitos": {
      "tipo": "crafting",
      "receitas_liberadas": [ 
         { "receita_id": "criar_machado1", "lvl": 1 },
         { "receita_id": "escudo_madeira", "lvl": 2 } 
      ]
    }
  }


}
